setup.py
pyrunes.egg-info/PKG-INFO
pyrunes.egg-info/SOURCES.txt
pyrunes.egg-info/dependency_links.txt
pyrunes.egg-info/requires.txt
pyrunes.egg-info/top_level.txt
runes/__init__.py
runes/exceptions.py
runes/runic_alphabets.py
runes/transliterate.py