Metadata-Version: 1.0
Name: pyrunes
Version: 0.3.0
Summary: Transliterate latin characters into runes
Home-page: https://github.com/IuryAlves/pyrunes
Author: Iury Alves
Author-email: iuryalves20@gmail.com
License: UNKNOWN
Platform: UNKNOWN
